lab5/part 5/alu.v
`include "mymul.v"

module Alu (ZERO, RESULT, DATA1, DATA2, SELECT, SLL);

// port declaration
input [7:0] DATA1, DATA2;
input [2:0] SELECT;
output reg [7:0] RESULT;
output  ZERO;
input SLL;



wire [7:0] ADD_OUT, FORWARD_OUT, AND_OUT, OR_OUT, SLL_OUT, SRL_OUT, SRA_OUT, ROR_OUT, MUL_OUT;


// module initialize
Forward fwd1(FORWARD_OUT, DATA2 );
Add add1(ADD_OUT, DATA1, DATA2 );
And and1(AND_OUT, DATA1, DATA2 );
Or or1(OR_OUT, DATA1, DATA2 );
sll slll1(SLL_OUT, DATA1, DATA2);
srl srl1(SRL_OUT, DATA1, DATA2);
sra sra1(SRA_OUT, DATA1, DATA2);
ror ror1(ROR_OUT, DATA1, DATA2);
multi mul1(MUL_OUT, DATA1, DATA2);



assign ZERO = ~(RESULT[0]|RESULT[1]|RESULT[2]|RESULT[3]|RESULT[4]|RESULT[5]|RESULT[6]|RESULT[7]);


always @(*) begin //always @(*) begin
    
    
    
      
    case (SELECT)
        'b000:
            RESULT = FORWARD_OUT;
        'b001:
            RESULT = ADD_OUT; 
        'b010:
            RESULT = AND_OUT; 
        'b011:
            RESULT = OR_OUT; 
        'b100:
            RESULT = MUL_OUT; 
        'b101:
            begin
                if(SLL) RESULT = SLL_OUT;
                else RESULT = SRL_OUT;
            end
        'b110:
            RESULT = SRA_OUT; 
        'b111:
            RESULT = ROR_OUT; 
        default:
            RESULT = 'b00000000;

    endcase

end


endmodule

// arithmatic modules

module Forward (FORWARD_OUT, DATA2);
    input [7:0]  DATA2;
    output [7:0] FORWARD_OUT;
    assign #1 FORWARD_OUT =  DATA2; 
    
endmodule

module Add (ADD_OUT, DATA1, DATA2);
    input [7:0] DATA1, DATA2;
    output [7:0] ADD_OUT;
    assign #2  ADD_OUT =  DATA1+DATA2; 
    
endmodule

module And (AND_OUT, DATA1, DATA2);
    input [7:0] DATA1, DATA2;
    output [7:0] AND_OUT;
    assign #1 AND_OUT =  DATA1 & DATA2; 
    
endmodule

module Or (OR_OUT, DATA1, DATA2);
    input [7:0] DATA1, DATA2;
    output [7:0] OR_OUT;
    assign  #1 OR_OUT =  DATA1 | DATA2; 
    
endmodule

module sra ( SRA_OUT, DATA1, DATA2 ); // arithmatic right shift
    input [7:0] DATA1, DATA2;
    output [7:0] SRA_OUT;
    reg [7:0] shifted;
    integer i,j;
    
    initial begin
        #1
        shifted = DATA1;  //copy data1
        
        for(i=0;i<DATA2;i=i+1)begin
            
            for(j=0;j<7;j=j+1)begin
                
                shifted[j]=shifted[j+1]; //one right arithmatic shift bit
            end
            shifted[7]=shifted[6];
        end
            
    end
    assign #1 SRA_OUT = shifted;
    
endmodule

module ror (ROR_OUT, DATA1, DATA2);
    input [7:0] DATA1, DATA2;
    output [7:0] ROR_OUT;
    reg [7:0] shifted;
    integer i,j;
    reg temp; 
    initial begin
        #1
        shifted = DATA1;  //copy data1
        for(i=0;i<DATA2;i=i+1)begin
            temp = shifted[0];  //memorize last bit
            for(j=0;j<7;j=j+1)begin
                shifted[j]=shifted[j+1]; //one right rotate shift bit
            end
            shifted[7]=temp;
        end
    end
    assign #1 ROR_OUT = shifted;
endmodule

module sll (SLL_OUT, DATA1, DATA2);
    input [7:0] DATA1, DATA2;
    output [7:0] SLL_OUT;
    reg [7:0] shifted;
    integer i,j;

    initial begin
        #1
        shifted = DATA1; //copy data1
        for(i=0;i<DATA2;i=i+1)begin
            for(j=7;j>0;j=j-1)begin
                shifted[j]=shifted[j-1]; // one left shift bit
            end
            shifted[0]=1'b0;
        end
    end
    assign #1 SLL_OUT = shifted;
endmodule

module srl (SRL_OUT, DATA1, DATA2);
    input [7:0] DATA1, DATA2;
    output [7:0] SRL_OUT;
    reg [7:0] shifted;
    integer i,j;

    initial begin
        #1
        shifted = DATA1;  //copy data1
        for(i=0;i<DATA2;i=i+1)begin
            for(j=0;j<7;j=j+1)begin
                shifted[j]=shifted[j+1];   //one right shift bit
            end
            shifted[7]=1'b0;
        end
    end
    assign #1  SRL_OUT = shifted;
    
endmodule

// module mult (MUL_OUT, DATA1, DATA2);
//     input [7:0] DATA1, DATA2;
//     output [7:0] MUL_OUT;
//     assign #1  MUL_OUT = DATA1 * DATA2; 
// endmodule

lab5/alu (2).v
/*
 *	
 *	Task 1
 *	ALU 
 *
 */

// or operation
module OR(or_Out,DATA1,DATA2);

        //port declaration
        input [7:0] DATA1,DATA2;
        output [7:0] or_Out;
//	initial begin
        assign or_Out = DATA1 | DATA2;
//	end
endmodule

// and operation
module AND(and_Out,DATA1,DATA2);
	
	//port declaration
        input [7:0] DATA1,DATA2;
        output [7:0] and_Out;
	//initial begin	
        assign and_Out = DATA1 & DATA2;
	//end
endmodule



// add operation
module ADD(add_Out,DATA1,DATA2);
	
	//port declaration
        input [7:0] DATA1,DATA2;
        output [7:0] add_Out;
//	initial begin	
	assign add_Out = DATA1 + DATA2;
//	end
endmodule

// foward operation
module FORWARD(fwd_Out, DATA2);
	
	//port declaration
	input [7:0] DATA2;
	output [7:0] fwd_Out;
	
//	initial begin
	assign fwd_Out = DATA2;
//	end
endmodule


module alu(RESULT,DATA1,DATA2,SELECT);

	//port declaration
	input [7:0] DATA1,DATA2;
	input [2:0] SELECT;
	output reg[7:0] RESULT;
	wire[7:0] fwd_Out, add_Out, and_Out, or_Out ;

	FORWARD fOp(fwd_Out, DATA2);
	ADD addOp(add_Out,DATA1,DATA2);
	AND andOp(and_Out,DATA1,DATA2);
	OR orOp(or_Out,DATA1,DATA2);

	always @ (*) begin
	
	case(SELECT) 

	'b000: 
		#1 RESULT =  fwd_Out ;

	
	'b001:
		#2 RESULT = add_Out ;		

	'b010:
		
		#1 RESULT =  and_Out ;
	
	'b011:
		
		#1 RESULT = or_Out ;

	default:

		RESULT = 'b00000000;	
		
	endcase
	end
	
endmodule

lab5/Chathura/testalu.v
`include "alu.v"


//testbench
module testbench;

        reg [7:0] DATA1, DATA2;
        reg [2:0] SELECT;
        wire [7:0] RESULT;

        alu myALU(RESULT,DATA1,DATA2,SELECT);

        initial
        begin


        $dumpfile("testALU.vcd"); // dumping the variables
        $dumpvars(0, testbench);



        DATA1 = 'b00101100;
        DATA2 = 'b01011011;

        SELECT = 'b000;
        #5 $display("DATA1 = %d, DATA2 = %d, SELECT = %d ---->  RESULT = %d \n",DATA1, DATA2, SELECT, RESULT);


        SELECT = 'b001;
        #5 $display("DATA1 = %d, DATA2 = %d, SELECT = %d ---->  RESULT = %d \n",DATA1, DATA2, SELECT, RESULT);


        SELECT = 'b010;
        #5 $display("DATA1 = %d, DATA2 = %d, SELECT = %d ---->  RESULT = %d \n",DATA1, DATA2, SELECT, RESULT);

        SELECT = 'b011;
        #5 $display("DATA1 = %d, DATA2 = %d, SELECT = %d ---->  RESULT = %d \n",DATA1, DATA2, SELECT, RESULT);

        $finish;
        end
endmodule

lab5/Chathura/testALU.vcd
$date
	Thu Jan  6 11:03:46 2022
$end
$version
	Icarus Verilog
$end
$timescale
	1s
$end
$scope module testbench $end
$var wire 8 ! RESULT [7:0] $end
$var reg 8 " DATA1 [7:0] $end
$var reg 8 # DATA2 [7:0] $end
$var reg 3 $ SELECT [2:0] $end
$scope module myALU $end
$var wire 8 % DATA1 [7:0] $end
$var wire 8 & DATA2 [7:0] $end
$var wire 3 ' SELECT [2:0] $end
$var wire 8 ( or_Out [7:0] $end
$var wire 8 ) fwd_Out [7:0] $end
$var wire 8 * and_Out [7:0] $end
$var wire 8 + add_Out [7:0] $end
$var reg 8 , RESULT [7:0] $end
$scope module addOp $end
$var wire 8 - DATA1 [7:0] $end
$var wire 8 . DATA2 [7:0] $end
$var wire 8 / add_Out [7:0] $end
$upscope $end
$scope module andOp $end
$var wire 8 0 DATA1 [7:0] $end
$var wire 8 1 DATA2 [7:0] $end
$var wire 8 2 and_Out [7:0] $end
$upscope $end
$scope module fOp $end
$var wire 8 3 DATA2 [7:0] $end
$var wire 8 4 fwd_Out [7:0] $end
$upscope $end
$scope module orOp $end
$var wire 8 5 DATA1 [7:0] $end
$var wire 8 6 DATA2 [7:0] $end
$var wire 8 7 or_Out [7:0] $end
$upscope $end
$upscope $end
$upscope $end
$enddefinitions $end
#0
$dumpvars
b1111111 7
b1011011 6
b101100 5
b1011011 4
b1011011 3
b1000 2
b1011011 1
b101100 0
b10000111 /
b1011011 .
b101100 -
bx ,
b10000111 +
b1000 *
b1011011 )
b1111111 (
b0 '
b1011011 &
b101100 %
b0 $
b1011011 #
b101100 "
bx !
$end
#1
b1011011 !
b1011011 ,
#5
b1 $
b1 '
#7
b10000111 !
b10000111 ,
#10
b10 $
b10 '
#11
b1000 !
b1000 ,
#15
b11 $
b11 '
#16
b1111111 !
b1111111 ,
