src/lab6/part2/mux_2to1_32bits.v
`timescale 1ns/100ps
module mux_2to1_32bits(RESULT, INPUT1, INPUT2, SELECT);

	// port declarartion
	input [31:0] INPUT1, INPUT2;
	input SELECT;
	output reg [31:0]RESULT;

	always @(*) begin
	
		if( SELECT == 1'b1 )
			
			RESULT = INPUT2;

		else

			RESULT = INPUT1;
	

	end	

endmodule

lab6/part3/new_adder.v
/*
 *
 *	Part 3
 *	New Adder with 2 units delay
 * 
 *
 */


module newAdder(RESULT, INPUT1, INPUT2);
	
	// port declaration
	input [31:0] INPUT1, INPUT2;
	output [31:0] RESULT;
	
	assign #2 RESULT = INPUT1 + INPUT2;

endmodule

src/lab6/part2/adder.v
/*
 *
 *	Part 3
 *	Adder
 * 
 *
 */
`timescale 1ns/100ps

module adder(RESULT, INPUT1, INPUT2);
	
	// port declaration
	input [31:0] INPUT1, INPUT2;
	output [31:0] RESULT;
	
	assign #1 RESULT = INPUT1 + INPUT2;

endmodule

lab5/old/group02_lab5_part4/group02_lab5_part4/alu.v
/*
 *	
 *	Task 1 - ALU
 *	
 */

// There are four modules for operations which are OR, AND, ADD and FORWARD.
// input and output are 8-bits

// bitwise or operation
module OR(or_Out,DATA1,DATA2);

        //port declaration
        input [7:0] DATA1,DATA2;
        output [7:0] or_Out;

        assign #1 or_Out = DATA1 | DATA2;	// 1 unit delay in the continuous assignment

endmodule

// bitwise and operation
module AND(and_Out,DATA1,DATA2);
	
	//port declaration
        input [7:0] DATA1,DATA2;
        output [7:0] and_Out;
	
        assign #1 and_Out = DATA1 & DATA2;	// 1 unit delay in the continuous assignment

endmodule



// add operation
module ADD(add_Out,DATA1,DATA2);
	
	//port declaration
        input [7:0] DATA1,DATA2;
        output [7:0] add_Out;
	
	assign #2 add_Out = DATA1 + DATA2;	// 2 unit delay in the continuous assignment

endmodule

// foward operation
module FORWARD(fwd_Out, DATA2);
	
	//port declaration
	input [7:0] DATA2;
	output [7:0] fwd_Out;
		
	assign #1 fwd_Out = DATA2;		// 1 unit delay in the continuous assignment
	
endmodule

// alu module 
// input data and output are 8-bits and select port is 3-bits
module alu(RESULT,ZERO,DATA1,DATA2,SELECT);

	//port declaration
	input [7:0] DATA1,DATA2;				// input data
	input [2:0] SELECT;					// select is which operation must do.
	output reg[7:0] RESULT;					// final ALU output
	output ZERO; 						// ZERO output
	wire[7:0] fwd_Out, add_Out, and_Out, or_Out 	;	// to get the output of operation modules
	
	// use above operation modules. 
	// DATA1, DATA2 are inputs. fwd_Out, add_Out, and_Out and or_Out are output.
	FORWARD fOp(fwd_Out, DATA2);
	ADD addOp(add_Out,DATA1,DATA2);
	AND andOp(and_Out,DATA1,DATA2);
	OR orOp(or_Out,DATA1,DATA2);


	assign ZERO = ~(RESULT[0]|RESULT[1]|RESULT[2]|RESULT[3]|RESULT[4]|RESULT[5]|RESULT[6]|RESULT[7]);


	always @(*) begin				// build the sensitivity list 
	
	case(SELECT) 					// switch case and all cases are in binary form

	'b000: 
		RESULT =  fwd_Out ;			// this is for forward operation
		
	
	'b001:
		RESULT = add_Out ;			// this is for add operation

	'b010:
		
		RESULT =  and_Out ;			// this is for bitwise and operation
	
	'b011:
		
		RESULT = or_Out ;			// this is for bitwise or operation

	default:

		RESULT = 'b00000000;			// defualt result = 0 
		
	endcase
	end
	
endmodule

lab6/part2/mux_2to1_8bits.v
/*
 *
 *	Part 3 
 *
 *	This is a MUX which has two inputs and one selection.
 *
 *
 */
`timescale 1ns/100ps
module mux_2to1_8bits(RESULT, INPUT1, INPUT2, SELECT);

	input [7:0] INPUT1, INPUT2;		// 8-bits inputs 
	input SELECT;				// selection pin
	output reg [7:0] RESULT;		// 8-bits output

	always @(*) 
	begin		
		
		if( SELECT == 1'b1 )		// SELECT == 1'b1
			
			RESULT = INPUT2 ;

		else if( SELECT == 1'b0 )			// SELECT = 1'b0

			RESULT = INPUT1 ;

	
	end	

endmodule

lab6/part3/twos_complement_converter.v
/*
 *
 *	Part 3
 *	2s complement converter
 *
 *
 */ 

module twos_complement_converter(RESULT, INPUT);
	
	// port declaration
	input [7:0] INPUT;
	output [7:0] RESULT;

	assign #1 RESULT = ~INPUT + 8'b1; 	// convert to 2s complement


endmodule

lab5/old/group02_lab5_part4/group02_lab5_part4/reg_file.v
/*
 *
 *	Part 2 - Register File
 *	Group 2
 *	E/18/402   E/18/397
 *
 *
 */

module reg_file(IN, OUT1, OUT2, INADDRESS, OUT1ADDRESS, OUT2ADDRESS, WRITE, CLK, RESET);

	input WRITE, CLK, RESET;				// 1-bit inputs
	input [2:0] INADDRESS, OUT1ADDRESS, OUT2ADDRESS;	// 3-bits inputs
	input [7:0] IN;						// 8-bits input

	output [7:0] OUT1, OUT2;				// 8-bits outputs


	reg [7:0] registers[7:0];		// this represents the 8-bits(1 byte)  8 registers ( 8x8 register file)


	integer regNum ;			// represet the register number for the RESET task

	// assign given addresses values to OUT1 and OUT2 respectively. this is asynchronous with delay 2 units
	assign #2 OUT1 = registers[OUT1ADDRESS];	
	assign #2 OUT2 = registers[OUT2ADDRESS];


	// write to given address register at positive edge of the clock
	always @(posedge CLK) 
	begin 
		

		// reset all the registers synchronously at the positive edge of the clock
		// reset all the registers when RESET is high with delay 1 units
		if ( RESET ) #1
		begin
			
			for(regNum = 0; regNum < 8 ; regNum = regNum + 1)begin
			
				registers[regNum] = 'b00000000;

			end
			
		end

		// writting happens when WRITE is high.
                // if statement includes only one row so don't use begin end keywords
                if ( WRITE == 'b1 && RESET == 'b0  )

                        // this is synchronous delay 1 unit.
                        // write in to given register
                        #1 registers[INADDRESS] = IN ;
	
	end

endmodule

lab5/old/group02_lab5_part4/group02_lab5_part4/control_unit.v
/*
 *
 *	Part 3
 *	CONTROL UNIT
 *
 */


module control_unit(ALUOP,MUX_2SCMPL,MUX_IMMD,WRITEENABLE,BEQ_ENABLE, JUMP_ENABLE, OP);

	input [7:0] OP;						// opcode

	output reg MUX_2SCMPL, MUX_IMMD, WRITEENABLE, BEQ_ENABLE, JUMP_ENABLE;		// 1 bit outputs from control unit
	output reg [2:0] ALUOP;					// 3-bits ALU opcode

	
	always @(*)
	begin 	
		
		#1

		case(OP)
			// case for load immediate value
			8'b00000000: begin
			
				ALUOP = 3'b000;		// alu operation code 
				MUX_2SCMPL = 'b0;	// 2s complement select pin
				MUX_IMMD = 'b1;		// immediadte value select pin
				WRITEENABLE = 'b1;	// register write enable pin
				BEQ_ENABLE = 'b0;	// branch equal enable pin
				JUMP_ENABLE = 'b0;	// jump enable pin

			end
			
			// case for move register value
			8'b00000001: begin

				ALUOP = 3'b000;		// alu operation code
                                MUX_2SCMPL = 'b0;	// 2s complement select pin
                                MUX_IMMD = 'b0;		// immediadte value select pin
                                WRITEENABLE = 'b1;	// register write enable pin
				BEQ_ENABLE = 'b0;       // branch equal enable pin
                                JUMP_ENABLE = 'b0;      // jump enable pin

			end

			// case for add operation
			8'b00000010: begin
				
				ALUOP = 3'b001;		// alu operation code
                                MUX_2SCMPL = 'b0;	// 2s complement select pin
                                MUX_IMMD = 'b0;		// immediadte value select pin
                                WRITEENABLE = 'b1;	// register write enable pin
				BEQ_ENABLE = 'b0;       // branch equal enable pin
                                JUMP_ENABLE = 'b0;      // jump enable pin

			end

			// case for sub operation
			8'b00000011: begin

				ALUOP = 3'b001;		// alu operation code
                                MUX_2SCMPL = 'b1;	// 2s complement select pin
                                MUX_IMMD = 'b0;		// immediadte value select pin
                                WRITEENABLE = 'b1;	// register write enable pin
				BEQ_ENABLE = 'b0;       // branch equal enable pin
                                JUMP_ENABLE = 'b0;      // jump enable pin
			
			end	


			// case for and operation
			8'b00000100: begin
				
				ALUOP = 3'b010;		// alu operation code
                                MUX_2SCMPL = 'b0;	// 2s complement select pin
                                MUX_IMMD = 'b0;		// immediadte value select pin
                                WRITEENABLE = 'b1;	// register write enable pin
				BEQ_ENABLE = 'b0;       // branch equal enable pin
                                JUMP_ENABLE = 'b0;      // jump enable pin

                        end

			// case for or operation
			8'b00000101: begin
				
				ALUOP = 3'b011;		// alu operation code
                                MUX_2SCMPL = 'b0;	// 2s complement select pin
                                MUX_IMMD = 'b0;		// immediadte value select pin
                                WRITEENABLE = 'b1;	// register write enable pin
				BEQ_ENABLE = 'b0;       // branch equal enable pin
                                JUMP_ENABLE = 'b0;      // jump enable pin

                        end

			// case for beq
			8'b00000111: begin

				ALUOP = 3'b001;         // alu operation code
                                MUX_2SCMPL = 'b1;       // 2s complement select pin
                                MUX_IMMD = 'b0;         // immediadte value select pin
                                WRITEENABLE = 'b0;      // register write enable pin
                                BEQ_ENABLE = 'b1;       // branch equal enable pin
                                JUMP_ENABLE = 'b0;      // jump enable pin

			end	

			// case for jump
			8'b00000110: begin

				ALUOP = 3'b111;         // alu operation code
                                MUX_2SCMPL = 'b0;       // 2s complement select pin
                                MUX_IMMD = 'b0;         // immediadte value select pin
                                WRITEENABLE = 'b0;      // register write enable pin
                                BEQ_ENABLE = 'b0;       // branch equal enable pin
                                JUMP_ENABLE = 'b1;      // jump enable pin

			end

				
		endcase
	end

endmodule

src/lab5/old/group02_lab5_part4/group02_lab5_part4/cpu.v
/*
 *
 *	Part 3
 *	CPU
 *
 */ 


`include "alu.v"
`include "adder.v"
`include "control_unit.v"
`include "mux_2to1_8bits.v"
`include "mux_2to1_32bits.v"
`include "reg_file.v"
`include "twos_complement_converter.v"
`include "new_adder.v"


module cpu(PC, INSTRUCTION, CLK, RESET);
	
	// port declarations
	input [31:0] INSTRUCTION;		// this is for 32 bits instruction
	input CLK, RESET;			// 1 bit clock and reset
	output reg[31:0] PC;			// 32 bits PC
	
	wire TWOs_ENABLE, IMMD_ENABLE, WRITEENABLE, ZERO, BEQ_ENABLE, JUMP_ENABLE, BEQ_SELECT,BEQ_JUMP_ENABLE;
	wire [2:0] ALUOP;
	wire [7:0] WRITEREG, READREG1, READREG2; 
	wire [7:0] OPCODE, ALU_RESULT, REGOUT1, REGOUT2, TWOs_CMPLEMENT, MUX1_RESULT, MUX2_RESULT, IMMEDIATE_VAL, WRITE_DATA;
	wire [31:0] PC_NEXT, JUMP_PC, PC_ADD_4;


	// initiating the modules
	control_unit my_cu ( ALUOP, TWOs_ENABLE, IMMD_ENABLE, WRITEENABLE, BEQ_ENABLE, JUMP_ENABLE, OPCODE);		   	// control unit module
	reg_file myreg (WRITE_DATA, REGOUT1, REGOUT2, WRITEREG[2:0], READREG1[2:0], READREG2[2:0], WRITEENABLE, CLK, RESET);	// 8x8 register file
	twos_complement_converter my2s_cmpl (TWOs_CMPLEMENT, REGOUT2);								// 2s complement unit
	mux_2to1_8bits my_2to1_mux1 (MUX1_RESULT, REGOUT2, TWOs_CMPLEMENT, TWOs_ENABLE);					// 2 to 1 MUX in complement value select unit
	mux_2to1_8bits my_2to1_mux2 (MUX2_RESULT ,MUX1_RESULT,IMMEDIATE_VAL, IMMD_ENABLE); 					// 2 to 1 MUX in immdiate value select unit
	alu my_alu (ALU_RESULT ,ZERO, REGOUT1, MUX2_RESULT, ALUOP);								// ALU unit
	adder pc_adder (PC_ADD_4 ,PC, 32'd4);											// instruction add by 4 unit (PC + 4)
	
	// { {22{WRITEREG[7]}},WRITEREG,2'b00} --> WRITEREG size is 8bits. We need 32 bits size instruction.
	//  Therefore, WRITEREG is sign extended and shifted by 2
	newAdder address_adder (JUMP_PC , { {22{WRITEREG[7]}},WRITEREG,2'b00}, PC_ADD_4 );					// add 2 instructions 
	mux_2to1_32bits mux_beq(PC_NEXT , PC_ADD_4, JUMP_PC, BEQ_JUMP_ENABLE);							// 32 bits size 2*1 mux 
	

	and a1(BEQ_SELECT, ZERO, BEQ_ENABLE);											// AND gate to beq enable and zero signal
	or o1(BEQ_JUMP_ENABLE,BEQ_SELECT,JUMP_ENABLE);										// OR gate to jump enable and AND gate signal


	assign WRITE_DATA = ALU_RESULT ;		// connect the alu output and register file write data
	
	// decoding instruction
	assign IMMEDIATE_VAL = INSTRUCTION[7:0];	// get immediate value
	assign READREG2 = INSTRUCTION[7:0];		// get RS
	assign READREG1 = INSTRUCTION[15:8];		// get RT
	assign WRITEREG = INSTRUCTION[23:16];		// get RD
	assign OPCODE = INSTRUCTION[31:24];             // get 8-bits op-code


	


	always @ ( posedge CLK ) begin
		
		if( RESET )	

			PC = 0 ;						// reset the PC
		
		else
	   		PC = #1 PC_NEXT ;				// increment the PC  

	end		


endmodule

lab5/cpu_tb.v
// Computer Architecture (CO224) - Lab 05
// Design: Testbench of Integrated CPU of Simple Processor
// Author: Isuru Nawinne

`include "cpu.v"

module cpu_tb;

    reg CLK, RESET;
    wire [31:0] PC ;
    wire [31:0] INSTRUCTION;
    
    /* 
    ------------------------
     SIMPLE INSTRUCTION MEM
    ------------------------
    */
    
    // TODO: Initialize an array of registers (8x1024) named 'instr_mem' to be used as instruction memory
	
	reg [7:0] instr_mem [1023:0]; 	// instruction array
    
    // TODO: Create combinational logic to support CPU instruction fetching, given the Program Counter(PC) value 
    //       (make sure you include the delay for instruction fetching here)
    
	assign #2 INSTRUCTION = {instr_mem[PC+3],instr_mem[PC+2],instr_mem[PC+1],instr_mem[PC]};	// fetching instruction with time delay
	
    initial
    begin
        // Initialize instruction memory with the set of instructions you need execute on CPU
        
        // METHOD 1: manually loading instructions to instr_mem
        //{instr_mem[10'd3], instr_mem[10'd2], instr_mem[10'd1], instr_mem[10'd0]} = 32'b00000000000001000000000000000101;
        //{instr_mem[10'd7], instr_mem[10'd6], instr_mem[10'd5], instr_mem[10'd4]} = 32'b00000000000000100000000000001001;
        //{instr_mem[10'd11], instr_mem[10'd10], instr_mem[10'd9], instr_mem[10'd8]} = 32'b00000010000001100000010000000010;
		
        // METHOD 2: loading instr_mem content from instr_mem.mem file
        $readmemb("instr_mem.mem", instr_mem);
    end
    
    /* 
    -----
     CPU
    -----
    */
    cpu mycpu(PC, INSTRUCTION, CLK, RESET);

    initial
    begin
    
        // generate files needed to plot the waveform using GTKWave
        $dumpfile("cpu_wavedata.vcd");
		$dumpvars(0, cpu_tb);
        
        CLK = 1'b0;
        RESET = 1'b0;
        
        // TODO: Reset the CPU (by giving a pulse to RESET signal) to start the program execution
        
	    RESET = 1'b1;
	    #5

	    RESET = 1'b0;
        // finish simulation after some time
        #500
        $finish;
        
    end

    
    // clock signal generation
    always
        #4 CLK = ~CLK;
        

endmodule

lab5/old/group02_lab5_part4/group02_lab5_part4/cpu_wavedata.vcd
$date
	Wed Feb  2 08:52:28 2022
$end
$version
	Icarus Verilog
$end
$timescale
	1s
$end
$scope module cpu_tb $end
$var wire 32 ! PC [31:0] $end
$var wire 32 " INSTRUCTION [31:0] $end
$var reg 1 # CLK $end
$var reg 1 $ RESET $end
$scope module mycpu $end
$var wire 1 % BEQ_JUMP_ENABLE $end
$var wire 1 & BEQ_SELECT $end
$var wire 1 # CLK $end
$var wire 32 ' INSTRUCTION [31:0] $end
$var wire 1 $ RESET $end
$var wire 8 ( WRITE_DATA [7:0] $end
$var wire 1 ) ZERO $end
$var wire 8 * WRITEREG [7:0] $end
$var wire 1 + WRITEENABLE $end
$var wire 1 , TWOs_ENABLE $end
$var wire 8 - TWOs_CMPLEMENT [7:0] $end
$var wire 8 . REGOUT2 [7:0] $end
$var wire 8 / REGOUT1 [7:0] $end
$var wire 8 0 READREG2 [7:0] $end
$var wire 8 1 READREG1 [7:0] $end
$var wire 32 2 PC_NEXT [31:0] $end
$var wire 32 3 PC_ADD_4 [31:0] $end
$var wire 8 4 OPCODE [7:0] $end
$var wire 8 5 MUX2_RESULT [7:0] $end
$var wire 8 6 MUX1_RESULT [7:0] $end
$var wire 32 7 JUMP_PC [31:0] $end
$var wire 1 8 JUMP_ENABLE $end
$var wire 8 9 IMMEDIATE_VAL [7:0] $end
$var wire 1 : IMMD_ENABLE $end
$var wire 1 ; BEQ_ENABLE $end
$var wire 8 < ALU_RESULT [7:0] $end
$var wire 3 = ALUOP [2:0] $end
$var reg 32 > PC [31:0] $end
$scope module address_adder $end
$var wire 32 ? INPUT1 [31:0] $end
$var wire 32 @ RESULT [31:0] $end
$var wire 32 A INPUT2 [31:0] $end
$upscope $end
$scope module mux_beq $end
$var wire 32 B INPUT2 [31:0] $end
$var wire 1 % SELECT $end
$var wire 32 C INPUT1 [31:0] $end
$var reg 32 D RESULT [31:0] $end
$upscope $end
$scope module my2s_cmpl $end
$var wire 8 E RESULT [7:0] $end
$var wire 8 F INPUT [7:0] $end
$upscope $end
$scope module my_2to1_mux1 $end
$var wire 8 G INPUT2 [7:0] $end
$var wire 1 , SELECT $end
$var wire 8 H INPUT1 [7:0] $end
$var reg 8 I RESULT [7:0] $end
$upscope $end
$scope module my_2to1_mux2 $end
$var wire 8 J INPUT1 [7:0] $end
$var wire 8 K INPUT2 [7:0] $end
$var wire 1 : SELECT $end
$var reg 8 L RESULT [7:0] $end
$upscope $end
$scope module my_alu $end
$var wire 8 M DATA2 [7:0] $end
$var wire 1 ) ZERO $end
$var wire 8 N or_Out [7:0] $end
$var wire 8 O fwd_Out [7:0] $end
$var wire 8 P and_Out [7:0] $end
$var wire 8 Q add_Out [7:0] $end
$var wire 3 R SELECT [2:0] $end
$var wire 8 S DATA1 [7:0] $end
$var reg 8 T RESULT [7:0] $end
$scope module addOp $end
$var wire 8 U DATA2 [7:0] $end
$var wire 8 V add_Out [7:0] $end
$var wire 8 W DATA1 [7:0] $end
$upscope $end
$scope module andOp $end
$var wire 8 X DATA2 [7:0] $end
$var wire 8 Y and_Out [7:0] $end
$var wire 8 Z DATA1 [7:0] $end
$upscope $end
$scope module fOp $end
$var wire 8 [ DATA2 [7:0] $end
$var wire 8 \ fwd_Out [7:0] $end
$upscope $end
$scope module orOp $end
$var wire 8 ] DATA2 [7:0] $end
$var wire 8 ^ or_Out [7:0] $end
$var wire 8 _ DATA1 [7:0] $end
$upscope $end
$upscope $end
$scope module my_cu $end
$var wire 8 ` OP [7:0] $end
$var reg 3 a ALUOP [2:0] $end
$var reg 1 ; BEQ_ENABLE $end
$var reg 1 8 JUMP_ENABLE $end
$var reg 1 , MUX_2SCMPL $end
$var reg 1 : MUX_IMMD $end
$var reg 1 + WRITEENABLE $end
$upscope $end
$scope module myreg $end
$var wire 1 # CLK $end
$var wire 8 b IN [7:0] $end
$var wire 3 c INADDRESS [2:0] $end
$var wire 8 d OUT1 [7:0] $end
$var wire 3 e OUT1ADDRESS [2:0] $end
$var wire 8 f OUT2 [7:0] $end
$var wire 3 g OUT2ADDRESS [2:0] $end
$var wire 1 $ RESET $end
$var wire 1 + WRITE $end
$var integer 32 h regNum [31:0] $end
$upscope $end
$scope module pc_adder $end
$var wire 32 i INPUT1 [31:0] $end
$var wire 32 j INPUT2 [31:0] $end
$var wire 32 k RESULT [31:0] $end
$upscope $end
$upscope $end
$upscope $end
$enddefinitions $end
#0
$dumpvars
bx k
b100 j
bx i
bx h
bx g
bx f
bx e
bx d
bx c
bx b
bx a
bx `
bx _
bx ^
bx ]
bx \
bx [
bx Z
bx Y
bx X
bx W
bx V
bx U
bx T
bx S
bx R
bx Q
bx P
bx O
bx N
bx M
bx L
bx K
bx J
bx I
bx H
bx G
bx F
bx E
bx D
bx C
bx B
bx A
bx @
bx00 ?
bx >
bx =
bx <
x;
x:
bx 9
x8
bx 7
bx 6
bx 5
bx 4
bx 3
bx 2
bx 1
bx 0
bx /
bx .
bx -
x,
x+
bx *
x)
bx (
bx '
x&
x%
1$
0#
bx "
bx !
$end
#4
b0 !
b0 >
b0 i
1#
#5
b100 2
b100 D
b1000 h
b100 3
b100 A
b100 C
b100 k
0$
#6
b101 g
b0 e
b100 c
b101 9
b101 K
b101 0
b0 1
b10000 ?
b100 *
b0 4
b0 `
b1000000000000000101 "
b1000000000000000101 '
#7
0%
0&
b101 5
b101 L
b101 M
b101 U
b101 X
b101 [
b101 ]
08
0;
1+
1:
0,
b0 =
b0 R
b0 a
#8
0)
b101 (
b101 b
b101 <
b101 T
b0 6
b0 I
b0 J
b0x0x P
b0x0x Y
bx1x1 N
bx1x1 ^
b101 O
b101 \
b0 .
b0 F
b0 H
b0 f
b0 /
b0 S
b0 W
b0 Z
b0 _
b0 d
b10100 7
b10100 @
b10100 B
0#
#9
b0 -
b0 E
b0 G
b101 N
b101 ^
b0 P
b0 Y
#10
b101 Q
b101 V
#12
1#
#13
b100 !
b100 >
b100 i
#14
b1000 2
b1000 D
b1000 3
b1000 A
b1000 C
b1000 k
#15
b101 c
b10100 ?
b101 *
b1010000000000000101 "
b1010000000000000101 '
#16
0#
#17
b11100 7
b11100 @
b11100 B
#20
1#
#21
b1000 !
b1000 >
b1000 i
#22
b1100 2
b1100 D
b1100 3
b1100 A
b1100 C
b1100 k
#23
b0 5
b0 L
b0 M
b0 U
b0 X
b0 [
b0 ]
b0 g
b10 c
b101 6
b101 I
b101 J
b0 9
b0 K
b0 0
b1000 ?
b10 *
b110 4
b110 `
b101 .
b101 F
b101 H
b101 f
b110000000100000000000000000 "
b110000000100000000000000000 '
#24
1)
b11100 2
b11100 D
1%
b101 5
b101 L
b101 M
b101 U
b101 X
b101 [
b101 ]
b0 (
b0 b
b0 <
b0 T
b0 N
b0 ^
b0 O
b0 \
18
0+
0:
b111 =
b111 R
b111 a
b11111011 -
b11111011 E
b11111011 G
0#
#25
b0 5
b0 L
b0 M
b0 U
b0 X
b0 [
b0 ]
b0 6
b0 I
b0 J
b10100 2
b10100 D
b101 N
b101 ^
b101 O
b101 \
b0 .
b0 F
b0 H
b0 f
b10100 7
b10100 @
b10100 B
#26
b0 N
b0 ^
b0 O
b0 \
b0 -
b0 E
b0 G
#27
b0 Q
b0 V
#28
1#
#29
b10100 !
b10100 >
b10100 i
#30
b11000 3
b11000 A
b11000 C
b11000 k
#31
b110 g
b0 c
b110 9
b110 K
b110 0
b0 ?
b0 *
b1 4
b1 `
b1000000000000000000000110 "
b1000000000000000000000110 '
#32
b11000 2
b11000 D
0%
08
1+
b0 =
b0 R
b0 a
0#
#33
b11000 7
b11000 @
b11000 B
#36
1#
#37
b11000 !
b11000 >
b11000 i
#38
b11100 2
b11100 D
b11100 3
b11100 A
b11100 C
b11100 k
#39
b101 g
b100 e
b110 c
b101 9
b101 K
b101 0
b100 1
b11111111111111111111111111111000 ?
b11111110 *
b111 4
b111 `
b111111111100000010000000101 "
b111111111100000010000000101 '
#40
b11000 2
b11000 D
1%
1&
1;
0+
1,
b1 =
b1 R
b1 a
0#
#41
b10100 2
b10100 D
b101 .
b101 F
b101 H
b101 f
b101 /
b101 S
b101 W
b101 Z
b101 _
b101 d
b10100 7
b10100 @
b10100 B
#42
b11111011 5
b11111011 L
b11111011 M
b11111011 U
b11111011 X
b11111011 [
b11111011 ]
b11111011 6
b11111011 I
b11111011 J
b11111011 -
b11111011 E
b11111011 G
b101 N
b101 ^
#43
b1 P
b1 Y
b11111111 N
b11111111 ^
b11111011 O
b11111011 \
#44
1#
#45
b10100 !
b10100 >
b10100 i
#46
b11000 3
b11000 A
b11000 C
b11000 k
#47
b110 g
b0 e
b0 c
b110 9
b110 K
b110 0
b0 1
b0 ?
b0 *
b1 4
b1 `
b1000000000000000000000110 "
b1000000000000000000000110 '
#48
0)
b11000 2
b11000 D
0%
b101 5
b101 L
b101 M
b101 U
b101 X
b101 [
b101 ]
0&
b101 6
b101 I
b101 J
b11111011 (
b11111011 b
b11111011 <
b11111011 T
0;
1+
0,
b0 =
b0 R
b0 a
0#
#49
b0 5
b0 L
b0 M
b0 U
b0 X
b0 [
b0 ]
b101 (
b101 b
b101 <
b101 T
b0 6
b0 I
b0 J
b101 P
b101 Y
b101 N
b101 ^
b101 O
b101 \
b0 .
b0 F
b0 H
b0 f
b0 /
b0 S
b0 W
b0 Z
b0 _
b0 d
b11000 7
b11000 @
b11000 B
#50
1)
b0 (
b0 b
b0 <
b0 T
b0 N
b0 ^
b0 O
b0 \
b0 -
b0 E
b0 G
b0 P
b0 Y
#52
1#
#53
b11000 !
b11000 >
b11000 i
#54
b11100 2
b11100 D
b11100 3
b11100 A
b11100 C
b11100 k
#55
b101 g
b100 e
b110 c
b101 9
b101 K
b101 0
b100 1
b11111111111111111111111111111000 ?
b11111110 *
b111 4
b111 `
b111111111100000010000000101 "
b111111111100000010000000101 '
#56
b11000 2
b11000 D
1%
1&
1;
0+
1,
b1 =
b1 R
b1 a
0#
#57
b10100 2
b10100 D
b101 .
b101 F
b101 H
b101 f
b101 /
b101 S
b101 W
b101 Z
b101 _
b101 d
b10100 7
b10100 @
b10100 B
#58
b11111011 5
b11111011 L
b11111011 M
b11111011 U
b11111011 X
b11111011 [
b11111011 ]
b11111011 6
b11111011 I
b11111011 J
b11111011 -
b11111011 E
b11111011 G
b101 N
b101 ^
#59
b1 P
b1 Y
b11111111 N
b11111111 ^
b11111011 O
b11111011 \
#60
1#
#61
b10100 !
b10100 >
b10100 i
#62
b11000 3
b11000 A
b11000 C
b11000 k
#63
b110 g
b0 e
b0 c
b110 9
b110 K
b110 0
b0 1
b0 ?
b0 *
b1 4
b1 `
b1000000000000000000000110 "
b1000000000000000000000110 '
#64
0)
b11000 2
b11000 D
0%
b101 5
b101 L
b101 M
b101 U
b101 X
b101 [
b101 ]
0&
b101 6
b101 I
b101 J
b11111011 (
b11111011 b
b11111011 <
b11111011 T
0;
1+
0,
b0 =
b0 R
b0 a
0#
#65
b0 5
b0 L
b0 M
b0 U
b0 X
b0 [
b0 ]
b101 (
b101 b
b101 <
b101 T
b0 6
b0 I
b0 J
b101 P
b101 Y
b101 N
b101 ^
b101 O
b101 \
b0 .
b0 F
b0 H
b0 f
b0 /
b0 S
b0 W
b0 Z
b0 _
b0 d
b11000 7
b11000 @
b11000 B
#66
1)
b0 (
b0 b
b0 <
b0 T
b0 N
b0 ^
b0 O
b0 \
b0 -
b0 E
b0 G
b0 P
b0 Y
#68
1#
#69
b11000 !
b11000 >
b11000 i
#70
b11100 2
b11100 D
b11100 3
b11100 A
b11100 C
b11100 k
#71
b101 g
b100 e
b110 c
b101 9
b101 K
b101 0
b100 1
b11111111111111111111111111111000 ?
b11111110 *
b111 4
b111 `
b111111111100000010000000101 "
b111111111100000010000000101 '
#72
b11000 2
b11000 D
1%
1&
1;
0+
1,
b1 =
b1 R
b1 a
0#
#73
b10100 2
b10100 D
b101 .
b101 F
b101 H
b101 f
b101 /
b101 S
b101 W
b101 Z
b101 _
b101 d
b10100 7
b10100 @
b10100 B
#74
b11111011 5
b11111011 L
b11111011 M
b11111011 U
b11111011 X
b11111011 [
b11111011 ]
b11111011 6
b11111011 I
b11111011 J
b11111011 -
b11111011 E
b11111011 G
b101 N
b101 ^
#75
b1 P
b1 Y
b11111111 N
b11111111 ^
b11111011 O
b11111011 \
#76
1#
#77
b10100 !
b10100 >
b10100 i
#78
b11000 3
b11000 A
b11000 C
b11000 k
#79
b110 g
b0 e
b0 c
b110 9
b110 K
b110 0
b0 1
b0 ?
b0 *
b1 4
b1 `
b1000000000000000000000110 "
b1000000000000000000000110 '
#80
0)
b11000 2
b11000 D
0%
b101 5
b101 L
b101 M
b101 U
b101 X
b101 [
b101 ]
0&
b101 6
b101 I
b101 J
b11111011 (
b11111011 b
b11111011 <
b11111011 T
0;
1+
0,
b0 =
b0 R
b0 a
0#
#81
b0 5
b0 L
b0 M
b0 U
b0 X
b0 [
b0 ]
b101 (
b101 b
b101 <
b101 T
b0 6
b0 I
b0 J
b101 P
b101 Y
b101 N
b101 ^
b101 O
b101 \
b0 .
b0 F
b0 H
b0 f
b0 /
b0 S
b0 W
b0 Z
b0 _
b0 d
b11000 7
b11000 @
b11000 B
#82
1)
b0 (
b0 b
b0 <
b0 T
b0 N
b0 ^
b0 O
b0 \
b0 -
b0 E
b0 G
b0 P
b0 Y
#84
1#
#85
b11000 !
b11000 >
b11000 i
#86
b11100 2
b11100 D
b11100 3
b11100 A
b11100 C
b11100 k
#87
b101 g
b100 e
b110 c
b101 9
b101 K
b101 0
b100 1
b11111111111111111111111111111000 ?
b11111110 *
b111 4
b111 `
b111111111100000010000000101 "
b111111111100000010000000101 '
#88
b11000 2
b11000 D
1%
1&
1;
0+
1,
b1 =
b1 R
b1 a
0#
#89
b10100 2
b10100 D
b101 .
b101 F
b101 H
b101 f
b101 /
b101 S
b101 W
b101 Z
b101 _
b101 d
b10100 7
b10100 @
b10100 B
#90
b11111011 5
b11111011 L
b11111011 M
b11111011 U
b11111011 X
b11111011 [
b11111011 ]
b11111011 6
b11111011 I
b11111011 J
b11111011 -
b11111011 E
b11111011 G
b101 N
b101 ^
#91
b1 P
b1 Y
b11111111 N
b11111111 ^
b11111011 O
b11111011 \
#92
1#
#93
b10100 !
b10100 >
b10100 i
#94
b11000 3
b11000 A
b11000 C
b11000 k
#95
b110 g
b0 e
b0 c
b110 9
b110 K
b110 0
b0 1
b0 ?
b0 *
b1 4
b1 `
b1000000000000000000000110 "
b1000000000000000000000110 '
#96
0)
b11000 2
b11000 D
0%
b101 5
b101 L
b101 M
b101 U
b101 X
b101 [
b101 ]
0&
b101 6
b101 I
b101 J
b11111011 (
b11111011 b
b11111011 <
b11111011 T
0;
1+
0,
b0 =
b0 R
b0 a
0#
#97
b0 5
b0 L
b0 M
b0 U
b0 X
b0 [
b0 ]
b101 (
b101 b
b101 <
b101 T
b0 6
b0 I
b0 J
b101 P
b101 Y
b101 N
b101 ^
b101 O
b101 \
b0 .
b0 F
b0 H
b0 f
b0 /
b0 S
b0 W
b0 Z
b0 _
b0 d
b11000 7
b11000 @
b11000 B
#98
1)
b0 (
b0 b
b0 <
b0 T
b0 N
b0 ^
b0 O
b0 \
b0 -
b0 E
b0 G
b0 P
b0 Y
#100
1#
#101
b11000 !
b11000 >
b11000 i
